{
  "type": "minecraft:crafting_shapeless",
  "group": "orikalkum_ingot",
  "ingredients": [
    {
      "item": "oresandmetals:orichalcite_scrap"
    },
    {
      "item": "oresandmetals:orichalcite_scrap"
    },
    {
      "item": "oresandmetals:orichalcite_scrap"
    },
    {
      "item": "oresandmetals:orichalcite_scrap"
    },
    {
      "item": "oresandmetals:raw_drakolith"
    },
    {
      "item": "oresandmetals:raw_drakolith"
    },
    {
      "item": "oresandmetals:raw_drakolith"
    },
    {
      "item": "oresandmetals:raw_drakolith"
    }
  ],
  "result": {
    "item": "oresandmetals:orikalkum_ingot"
  }
}