{
  "type": "minecraft:blasting",
  "ingredient": [
    {
      "item": "oresandmetals:steel_pickaxe"
    },
    {
      "item": "oresandmetals:steel_shovel"
    },
    {
      "item": "oresandmetals:steel_axe"
    },
    {
      "item": "oresandmetals:steel_hoe"
    },
    {
      "item": "oresandmetals:steel_sword"
    },
    {
      "item": "oresandmetals:steel_helmet"
    },
    {
      "item": "oresandmetals:steel_chestplate"
    },
    {
      "item": "oresandmetals:steel_leggings"
    },
    {
      "item": "oresandmetals:steel_boots"
    }
  ],
  "result": "oresandmetals:steel_nugget",
  "experience": 0.1,
  "cookingtime": 100
}