{
  "parent": "minecraft:recipes/root",
  "criteria": {
    "has_orichalcite_scrap": {
      "conditions": {
        "items": [
          {
            "items": [
              "oresandmetals:orichalcite_scrap"
            ]
          }
        ]
      },
      "trigger": "minecraft:inventory_changed"
    },
    "has_raw_drakolith": {
      "conditions": {
        "items": [
          {
            "items": [
              "oresandmetals:raw_drakolith"
            ]
          }
        ]
      },
      "trigger": "minecraft:inventory_changed"
    },
    "has_runite_ingot": {
      "conditions": {
        "items": [
          {
            "items": [
              "oresandmetals:runite_ingot"
            ]
          }
        ]
      },
      "trigger": "minecraft:inventory_changed"
    },
    "has_the_recipe": {
      "conditions": {
        "recipe": "minecraft:orikalkum_upgrade_smithing_template"
      },
      "trigger": "minecraft:recipe_unlocked"
    }
  },
  "requirements": [
    [
      "has_raw_drakolith",
      "has_runite_ingot",
      "has_orichalcite_scrap",
      "has_the_recipe"
    ]
  ],
  "rewards": {
    "recipes": [
      "minecraft:orikalkum_upgrade_smithing_template"
    ]
  },
  "sends_telemetry_event": false
}